adb_cloud_connector/__init__.py
adb_cloud_connector/utils.py
adb_cloud_connector/version.py
adb_cloud_connector/data/creds.json
adb_cloud_connector-1.0.2.dist-info/LICENSE
adb_cloud_connector-1.0.2.dist-info/METADATA
adb_cloud_connector-1.0.2.dist-info/WHEEL
adb_cloud_connector-1.0.2.dist-info/top_level.txt
adb_cloud_connector-1.0.2.dist-info/RECORD
