Metadata-Version: 2.1
Name: adb_cloud_connector
Version: 1.0.2
Summary: Access to temporary ArangoDB Cloud instance provisioning.
Home-page: https://github.com/arangodb/adb_cloud_connector
Author: Anthony Mahanna
Author-email: anthony.mahanna@arangodb.com
License: Apache Software License
Keywords: arangodb,cloud,connector
Platform: UNKNOWN
Classifier: Intended Audience :: Developers
Classifier: License :: OSI Approved :: Apache Software License
Classifier: Operating System :: OS Independent
Classifier: Programming Language :: Python :: 3
Classifier: Programming Language :: Python :: 3.6
Classifier: Programming Language :: Python :: 3.7
Classifier: Programming Language :: Python :: 3.8
Classifier: Programming Language :: Python :: 3.9
Classifier: Programming Language :: Python :: 3.10
Classifier: Topic :: Utilities
Classifier: Typing :: Typed
Requires-Python: >=3.6
Provides-Extra: dev
